exphub/__init__.py
exphub/aggregators/__init__.py
exphub/aggregators/aggregators.py
exphub/download/__init__.py
exphub/download/downloader.py
exphub/download/experiment.py
exphub/download/neptune_downloader.py
exphub/utils/__init__.py
exphub/utils/noise.py
exphub/utils/paths.py
exphub/vizualization/__init__.py
exphub/vizualization/wizzards.py
exphub-0.1.5.dist-info/LICENSE
exphub-0.1.5.dist-info/METADATA
exphub-0.1.5.dist-info/WHEEL
exphub-0.1.5.dist-info/RECORD
